argparse2tool/__init__.py
argparse2tool/check_path.py
argparse2tool/cmdline2cwl/__init__.py
argparse2tool/cmdline2cwl/cwl_tool.py
argparse2tool/cmdline2cwl/templates/cwltool.j2
argparse2tool/cmdline2cwl/templates/cwltool_inputs.j2
argparse2tool/cmdline2cwl/templates/cwltool_outputs.j2
argparse2tool/cmdline2gxml/__init__.py
argparse2tool/dropins/argparse/__init__.py
argparse2tool/dropins/argparse/argparse_cwl_translation.py
argparse2tool/dropins/argparse/argparse_galaxy_translation.py
argparse2tool/dropins/click/__init__.py
argparse2tool/dropins/click/click_cwl_translation.py
argparse2tool-0.5.2.data/data/LICENSE.TXT
argparse2tool-0.5.2.dist-info/LICENSE.TXT
argparse2tool-0.5.2.dist-info/METADATA
argparse2tool-0.5.2.dist-info/WHEEL
argparse2tool-0.5.2.dist-info/entry_points.txt
argparse2tool-0.5.2.dist-info/top_level.txt
argparse2tool-0.5.2.dist-info/RECORD
