Metadata-Version: 2.1
Name: argparse2tool
Version: 0.5.2
Summary: Instrument for forming Galaxy XML and CWL tool descriptions from argparse arguments
Home-page: https://github.com/hexylena/argparse2tool
Author: Helena Rasche, Anton Khodak
Author-email: hexylena@galaxians.org
Classifier: Development Status :: 4 - Beta
Classifier: Operating System :: OS Independent
Classifier: Intended Audience :: Developers
Classifier: Environment :: Console
Classifier: License :: OSI Approved :: Apache Software License
License-File: LICENSE.TXT
Requires-Dist: galaxyxml ==0.4.6
Requires-Dist: jinja2
